[		          {"image":"images/doc1.jpg", 
		          "name": "RxDx Hospital", 
		          "type": "Dentist", 
		          "address": "Grahite India", 
		          "contact": "9535443002", 
		          "ambulance": "9535443002", 
		          "rating": 3},
		          {"image":"images/doc1.jpg", 
		          "name": "doctor XYZXYZ", 
		          "type": "Dentist", 
		          "address": "Grahite India", 
		          "contact": "9535443002", 
		          "ambulance": "9535443002", 
		          "rating": 3},
		          {"image":"images/doc1.jpg", 
		          "name": "RxDx Hospital", 
		          "type": "Dentist", 
		          "address": "Grahite India", 
		          "contact": "9535443002", 
		          "ambulance": "9535443002", 
		          "rating": 3},
		          {"image":"images/doc1.jpg", 
		          "name": "RxDx Hospital", 
		          "type": "Dentist", 
		          "address": "Grahite India", 
		          "contact": "9535443002", 
		          "ambulance": "9535443002", 
		          "rating": 3},
		          {"image":"images/doc1.jpg", 
		          "name": "RxDx Hospital", 
		          "type": "Dentist", 
		          "address": "Grahite India", 
		          "contact": "9535443002", 
		          "ambulance": "9535443002", 
		          "rating": 3},
		          {"image":"images/doc1.jpg", 
		          "name": "RxDx Hospital", 
		          "type": "Dentist", 
		          "address": "Grahite India", 
		          "contact": "9535443002", 
		          "ambulance": "9535443002", 
		          "rating": 3}
		          
		    ]
